linktransformer/__init__.py
linktransformer/cluster_fns.py
linktransformer/infer.py
linktransformer/model_card_templates.py
linktransformer/preprocess.py
linktransformer/train_clf_model.py
linktransformer/train_model.py
linktransformer/utils.py
linktransformer/configs/__init__.py
linktransformer/configs/classification.json
linktransformer/configs/linkage.json
linktransformer/data/__init__.py
linktransformer/data/coarse.csv
linktransformer/data/company_clusters.csv
linktransformer/data/es_mexican_products.xlsx
linktransformer/data/eval_weather.csv
linktransformer/data/fine.csv
linktransformer/data/jp_pr_tk431.csv
linktransformer/data/jp_pr_tkv2.csv
linktransformer/data/protest_test.csv
linktransformer/data/protest_train.csv
linktransformer/data/protest_val.csv
linktransformer/data/protests_toy_sample_binary.csv
linktransformer/data/protests_toy_sample_ternary.csv
linktransformer/data/test_weather.csv
linktransformer/data/toy_comp_1.csv
linktransformer/data/toy_comp_2.csv
linktransformer/data/toy_multi_1.csv
linktransformer/data/toy_multi_2.csv
linktransformer/data/toy_pairs.csv
linktransformer/data/train_weather.csv
linktransformer/data/translation_1.csv
linktransformer/data/translation_2.csv
linktransformer/modelling/LinkTransformer.py
linktransformer/modelling/LinkTransformerClassifier.py
linktransformer/modelling/__init__.py
linktransformer/modified_sbert/__init__.py
linktransformer/modified_sbert/data_loaders.py
linktransformer/modified_sbert/evaluation.py
linktransformer/modified_sbert/losses.py
linktransformer/modified_sbert/train.py
linktransformer-0.1.17.dist-info/LICENSE
linktransformer-0.1.17.dist-info/METADATA
linktransformer-0.1.17.dist-info/WHEEL
linktransformer-0.1.17.dist-info/top_level.txt
linktransformer-0.1.17.dist-info/RECORD
