Metadata-Version: 2.2
Name: linktransformer
Version: 0.1.17
Summary: A friendly way to do link, aggregate, cluster and de-duplicate dataframes using large language models.
Author-email: Abhishek Arora and Melissa Dell <linktransformer23@gmail.com>
License:                     GNU GENERAL PUBLIC LICENSE
Project-URL: Homepage, https://linktransformer.github.io/
Classifier: Programming Language :: Python :: 3
Classifier: License :: OSI Approved :: MIT License
Classifier: Operating System :: OS Independent
Requires-Python: <3.12,>=3.8
License-File: LICENSE
Requires-Dist: scikit-learn==1.3.2
Requires-Dist: faiss-cpu==1.8.0
Requires-Dist: hdbscan==0.8.36
Requires-Dist: networkx==3.1
Requires-Dist: torch==2.5.1
Requires-Dist: sentence-transformers==2.3.1
Requires-Dist: transformers==4.48.1
Requires-Dist: wandb==0.17.0
Requires-Dist: numpy==1.24.4
Requires-Dist: pandas==2.2.3
Requires-Dist: httpx==0.27.2
Requires-Dist: openai==1.30.4
Requires-Dist: openpyxl==3.1.2
Requires-Dist: datasets==3.2.0
Requires-Dist: accelerate==1.3.0
Requires-Dist: evaluate==0.4.3
